PyOKR/OKR_osx.py
PyOKR/OKR_win.py
PyOKR/__init__.py
pyokr-1.1.4.dist-info/licenses/LICENSE.txt
pyokr-1.1.4.dist-info/METADATA
pyokr-1.1.4.dist-info/WHEEL
pyokr-1.1.4.dist-info/top_level.txt
pyokr-1.1.4.dist-info/RECORD
